substitutionstring/__init__.py
substitutionstring/compression_tools.py
substitutionstring/substitution.py
substitutionstring/substitution_sequence.py
substitutionstring/substitution_string.py
substitutionstring/substitution_tools.py
test/__init__.py
test/test_SubstitutionString.py
test/test_combine_permute.py
test/test_compression_tools.py
test/test_substitution.py
test/test_substitution_sequence.py
test/test_substitution_tools.py
substitutionstring-0.2.0.dist-info/LICENSE
substitutionstring-0.2.0.dist-info/METADATA
substitutionstring-0.2.0.dist-info/WHEEL
substitutionstring-0.2.0.dist-info/top_level.txt
substitutionstring-0.2.0.dist-info/RECORD
