Metadata-Version: 2.1
Name: substitutionstring
Version: 0.2.0
Summary: Manipulate substitution of string, as for instance deletion and insertion, without loss of information, and allow some algebra of the underneath Substitution object. Can be usefull for any manipulation of string, as version control system, natural language processing, or string comparison in a general sense. The simplest way of using this package is throw the SubstitutionString object, which handles the machinery of the Substitution applied to a given string.
Home-page: https://framagit.org/nlp/substitutionstring
Author: François Konschelle, Unité IAM, CHU-Bordeaux, France
Author-email: via.issue@only.please
License: GNU GENERAL PUBLIC LICENSE v.3
Platform: UNKNOWN
Classifier: Programming Language :: Python :: 3
Classifier: License :: OSI Approved :: GNU General Public License v3 (GPLv3)
Classifier: Operating System :: OS Independent
Classifier: Topic :: Scientific/Engineering :: Information Analysis
Classifier: Topic :: Text Processing
Classifier: Intended Audience :: Information Technology
Classifier: Intended Audience :: Science/Research
Requires-Python: >=3.6
License-File: LICENSE
